nzproxy/__init__.py
nzproxy/__version__.py
nzproxy-1b0.dev1.data/data/requirements.txt
nzproxy-1b0.dev1.dist-info/METADATA
nzproxy-1b0.dev1.dist-info/WHEEL
nzproxy-1b0.dev1.dist-info/entry_points.txt
nzproxy-1b0.dev1.dist-info/top_level.txt
nzproxy-1b0.dev1.dist-info/RECORD
