Metadata-Version: 2.1
Name: nzproxy
Version: 1b0.dev1
Summary: Proxies for python objects
Home-page: UNKNOWN
Author: Clement
Author-email: neze+pypi@melix.org
License: UNKNOWN
Platform: UNKNOWN
Classifier: Programming Language :: Python :: 3
